jupyterlab_sentry/__init__.py
jupyterlab_sentry/_version.py
jupyterlab_sentry-1.1.0.data/data/share/jupyter/labextensions/jupyterlab-sentry/package.json
jupyterlab_sentry-1.1.0.data/data/share/jupyter/labextensions/jupyterlab-sentry/schemas/jupyterlab-sentry/package.json.orig
jupyterlab_sentry-1.1.0.data/data/share/jupyter/labextensions/jupyterlab-sentry/schemas/jupyterlab-sentry/plugin.json
jupyterlab_sentry-1.1.0.data/data/share/jupyter/labextensions/jupyterlab-sentry/static/523.0588aab52f6ab34e6b26.js
jupyterlab_sentry-1.1.0.data/data/share/jupyter/labextensions/jupyterlab-sentry/static/544.e25f72e1c3ca66a26d25.js
jupyterlab_sentry-1.1.0.data/data/share/jupyter/labextensions/jupyterlab-sentry/static/544.e25f72e1c3ca66a26d25.js.LICENSE.txt
jupyterlab_sentry-1.1.0.data/data/share/jupyter/labextensions/jupyterlab-sentry/static/568.7b3fc6eb7b4dce4e5528.js
jupyterlab_sentry-1.1.0.data/data/share/jupyter/labextensions/jupyterlab-sentry/static/747.04addcdf88120f8c959d.js
jupyterlab_sentry-1.1.0.data/data/share/jupyter/labextensions/jupyterlab-sentry/static/996.2b50a71cc26af990c567.js
jupyterlab_sentry-1.1.0.data/data/share/jupyter/labextensions/jupyterlab-sentry/static/remoteEntry.7922cdab2577075c94d2.js
jupyterlab_sentry-1.1.0.data/data/share/jupyter/labextensions/jupyterlab-sentry/static/style.js
jupyterlab_sentry-1.1.0.data/data/share/jupyter/labextensions/jupyterlab-sentry/static/third-party-licenses.json
jupyterlab_sentry-1.1.0.data/data/share/jupyter/labextensions/jupyterlab-sentry/install.json
jupyterlab_sentry-1.1.0.dist-info/METADATA
jupyterlab_sentry-1.1.0.dist-info/WHEEL
jupyterlab_sentry-1.1.0.dist-info/licenses/LICENSE
jupyterlab_sentry-1.1.0.dist-info/RECORD
