Metadata-Version: 2.1
Name: jupyterlab_sentry
Version: 1.1.0
Summary: Sentry integration for jupyter lab
Project-URL: Homepage, https://github.com/team-monolith-product/jupyterlab-sentry
Project-URL: Bug Tracker, https://github.com/team-monolith-product/jupyterlab-sentry/issues
Project-URL: Repository, https://github.com/team-monolith-product/jupyterlab-sentry.git
Author-email: ChangHwan Lee <lch@team-mono.com>
License: BSD 3-Clause License
License-File: LICENSE
Classifier: Framework :: Jupyter
Classifier: Framework :: Jupyter :: JupyterLab
Classifier: Framework :: Jupyter :: JupyterLab :: 3
Classifier: Framework :: Jupyter :: JupyterLab :: Extensions
Classifier: Framework :: Jupyter :: JupyterLab :: Extensions :: Prebuilt
Classifier: License :: OSI Approved :: BSD License
Classifier: Programming Language :: Python
Classifier: Programming Language :: Python :: 3
Classifier: Programming Language :: Python :: 3.7
Classifier: Programming Language :: Python :: 3.8
Classifier: Programming Language :: Python :: 3.9
Classifier: Programming Language :: Python :: 3.10
Classifier: Programming Language :: Python :: 3.11
Requires-Python: >=3.7
